tox_matrix-0.1.1.data/scripts/tox-matrix
tox_matrix-0.1.1.dist-info/METADATA
tox_matrix-0.1.1.dist-info/top_level.txt
tox_matrix-0.1.1.dist-info/pydist.json
tox_matrix-0.1.1.dist-info/RECORD
tox_matrix-0.1.1.dist-info/WHEEL
tox_matrix-0.1.1.dist-info/DESCRIPTION.rst
tox_matrix-0.1.1.dist-info/entry_points.txt
toxmatrix/__init__.py
toxmatrix/template.py
toxmatrix/lib.py
toxmatrix/cli.py
