Metadata-Version: 2.0
Name: tox-matrix
Version: 0.1.1
Summary: Project for creating tox.ini files with multiple dependencies
Home-page: https://github.com/slafs/tox-matrix
Author: Slawek Ehlert
Author-email: slafs@op.pl
License: BSD
Keywords: tox-matrix
Platform: UNKNOWN
Classifier: Development Status :: 2 - Pre-Alpha
Classifier: Intended Audience :: Developers
Classifier: License :: OSI Approved :: BSD License
Classifier: Natural Language :: English
Classifier: Programming Language :: Python :: 2
Classifier: Programming Language :: Python :: 2.6
Classifier: Programming Language :: Python :: 2.7
Classifier: Programming Language :: Python :: 3
Classifier: Programming Language :: Python :: 3.3
Requires-Dist: docopt (>=0.6.1,<1.0.0)
Requires-Dist: Jinja2 (>=2.7.2,<3.0)
